Workbook

Sheet PARÂMETROS
A1: CMV por produto — O Beco Gelato
A2: Revisão de 21/10/2026. As células amarelas são suas — mude e tudo recalcula.
A4: Parâmetro | B4: Valor | C4: Unidade | D4: O que é
A5: Gelato por pote | B5: 140 | C5: g | D5: Medido em 16/10 com 35 potes. O Alfajor tem 135 g e é tratado à parte.
A6: Perda de processo | B6: 3 | C6: % | D6: O que fica na cuba, na pá e na espátula. Medido a 3% em lote grande; em lote de 1,5 kg chega a 10%.
A7: Imposto (Simples) | B7: 4.5 | C7: % | D7: Anexo II, 1ª faixa. CONFIRMAR com o contador.
A9: EMBALAGEM — por pote
A10: Item | B10: Qtd por pote | C10: R$ unitário | D10: R$ por pote
A11: Pote 150 ml com tampa | B11: 1 | C11: 1.07 | D11: =B11*C11
A12: Colher tradicional | B12: 1 | C12: 0.26 | D12: =B12*C12
A13: Lacre de sabor | B13: 1 | C13: 0.34 | D13: =B13*C13
A14: TOTAL EMBALAGEM | D14: =SUM(D11:D13)
A16: COMO A CONTA É FEITA
A17: Calda por pote = gelato por pote ÷ (1 − perda)
A18: Custo de insumo = soma de (g de cada ingrediente no pote × R$/kg ÷ 1000)
A19: CMV = insumo + embalagem
A20: Imposto = preço de venda × alíquota
A21: Contribuição = preço − CMV − imposto
A22: Margem = contribuição ÷ preço

Sheet PREÇOS
A1: Preço dos insumos
A2: Coluna amarela: edite aqui quando o preço mudar. Todos os produtos recalculam.
A4: Insumo | B4: R$ por kg | C4: Observação
A5: AGUA | B5: 0 | C5: SEM PREÇO — a conta sai menor que o real
A6: BASE MEC PROTEIN | B6: 148.2
A7: BISCOITO ALFAJOR DE CHOCOLATE (ZERO LACTOSE) | B7: 38.46
A8: CACAU 22/24 | B8: 130
A9: CREME DE LEITE FRESCO 35% ZL (VERDE CAMPO LACFREE) | B9: 57.8
A10: CREMOBENE PREMIUM (LIGA NEUTRA) | B10: 105.84
A11: DELÍCIA DE AMENDOIM PROTEICO | B11: 94.25
A12: DOCE DE LEITE VIÇOSA ZERO | B12: 99.75
A13: ERITRITOL | B13: 53.76
A14: GLICEROL (GLICERINA BIDESTILADA) | B14: 24
A15: GUSTO LIMONE SICILIA (PÓ) | B15: 359.62
A16: LEITE EM PO DESNATADO ZL (BATAVO PENSE ZERO) | B16: 65.7
A17: LEITE ZERO LACTOSE (INTEGRAL) | B17: 9.8
... A28: STEVIA | B28: 3100

Sheet VENDA
A1: Preço de venda por produto
A2: Preço praticado na rua, confirmado em 21/10. Edite para simular.
A4: Produto | B4: Linha | C4: R$ atacado | D4: R$ varejo sugerido
A5: Café Proteico | B5: BOOST | C5: 20.5 | D5: 32.9
A6: Pistache | B6: SPECIAL | C6: 20.5 | D6: 32.9
A7: Manga com Maracujá | B7: FRESH | C7: 18.7 | D7: 29.9
A8: Sorbet Morango | B8: FRESH | C8: 18.7 | D8: 29.9
A9: Torta de Limão | B9: SPECIAL | C9: 20.5 | D9: 32.9
A10: Alfajor | B10: SPECIAL | C10: 20.5 | D10: 32.9
A11: Brigadeiro Proteico | B11: BOOST | C11: 20.5 | D11: 32.9

Sheet RESUMO
A1: CMV e margem — os 7 produtos
A2: Tudo puxado das abas de produto. Mude um preço na aba PREÇOS e esta tabela acompanha.
A4: Produto | B4: Linha | C4: Pote (g) | D4: CMV | E4: Venda | F4: CMV % | G4: Imposto | H4: Contribuição | I4: Margem
A5: Café Proteico | B5: BOOST | C5: 140 | D5: ='CMV Café Proteico'!B21 | E5: ='CMV Café Proteico'!B22 | F5: =IFERROR(D5/E5,0) | G5: =E5*PARÂMETROS!$B$7/100 | H5: ='CMV Café Proteico'!B24 | I5: =IFERROR(H5/E5,0)
A6: Pistache | B6: SPECIAL | C6: 140 | D6: ='CMV Pistache'!B19 | E6: ='CMV Pistache'!B20 | F6: =IFERROR(D6/E6,0) | G6: =E6*PARÂMETROS!$B$7/100 | H6: ='CMV Pistache'!B22 | I6: =IFERROR(H6/E6,0)
A7: Manga com Maracujá | B7: FRESH | C7: 140 | D7: ='CMV Manga com Maracujá'!B18 | E7: ='CMV Manga com Maracujá'!B19 | F7: =IFERROR(D7/E7,0) | G7: =E7*PARÂMETROS!$B$7/100 | H7: ='CMV Manga com Maracujá'!B21 | I7: =IFERROR(H7/E7,0)
A8: Sorbet Morango | B8: FRESH | C8: 140 | D8: ='CMV Sorbet Morango'!B18 | E8: ='CMV Sorbet Morango'!B19 | F8: =IFERROR(D8/E8,0) | G8: =E8*PARÂMETROS!$B$7/100 | H8: ='CMV Sorbet Morango'!B21 | I8: =IFERROR(H8/E8,0)
A9: Torta de Limão | B9: SPECIAL | C9: 140 | D9: ='CMV Torta de Limão'!B19 | E9: ='CMV Torta de Limão'!B20 | F9: =IFERROR(D9/E9,0) | G9: =E9*PARÂMETROS!$B$7/100 | H9: ='CMV Torta de Limão'!B22 | I9: =IFERROR(H9/E9,0)
A10: Alfajor | B10: SPECIAL | C10: 150 | D10: ='CMV Alfajor'!B22 | E10: ='CMV Alfajor'!B23 | F10: =IFERROR(D10/E10,0) | G10: =E10*PARÂMETROS!$B$7/100 | H10: ='CMV Alfajor'!B25 | I10: =IFERROR(H10/E10,0)
A11: Brigadeiro Proteico | B11: BOOST | C11: 140 | D11: ='CMV Brigadeiro Proteico'!B20 | E11: ='CMV Brigadeiro Proteico'!B21 | F11: =IFERROR(D11/E11,0) | G11: =E11*PARÂMETROS!$B$7/100 | H11: ='CMV Brigadeiro Proteico'!B23 | I11: =IFERROR(H11/E11,0)
A12: MÉDIA DA LINHA | D12: =AVERAGE(D5:D11) | E12: =AVERAGE(E5:E11) | F12: =AVERAGE(F5:F11) | H12: =AVERAGE(H5:H11) | I12: =AVERAGE(I5:I11)
A14: SIMULAÇÃO DE PRODUÇÃO
A15: Produto | B15: Potes a produzir | C15: Calda (g) | D15: Custo de insumo | E15: Custo total | F15: Receita | G15: Contribuição
A16: Café Proteico | B16: 0 | C16: =B16*125.5605/(1-PARÂMETROS!$B$6/100) | D16: =B16*('CMV Café Proteico'!B21-PARÂMETROS!$D$14) | E16: =B16*'CMV Café Proteico'!B21 | F16: =B16*E5 | G16: =B16*'CMV Café Proteico'!B24
A17: Pistache | B17: 0 | C17: =B17*140.0000/(1-PARÂMETROS!$B$6/100) | D17: =B17*('CMV Pistache'!B19-PARÂMETROS!$D$14) | E17: =B17*'CMV Pistache'!B19 | F17: =B17*E6 | G17: =B17*'CMV Pistache'!B22
A18: Manga com Maracujá | B18: 0 | C18: =B18*140.0000/(1-PARÂMETROS!$B$6/100) | D18: =B18*('CMV Manga com Maracujá'!B18-PARÂMETROS!$D$14) | E18: =B18*'CMV Manga com Maracujá'!B18 | F18: =B18*E7 | G18: =B18*'CMV Manga com Maracujá'!B21
A19: Sorbet Morango | B19: 0 | C19: =B19*140.0000/(1-PARÂMETROS!$B$6/100) | D19: =B19*('CMV Sorbet Morango'!B18-PARÂMETROS!$D$14) | E19: =B19*'CMV Sorbet Morango'!B18 | F19: =B19*E8 | G19: =B19*'CMV Sorbet Morango'!B21
A20: Torta de Limão | B20: 0 | C20: =B20*140.0000/(1-PARÂMETROS!$B$6/100) | D20: =B20*('CMV Torta de Limão'!B19-PARÂMETROS!$D$14) | E20: =B20*'CMV Torta de Limão'!B19 | F20: =B20*E9 | G20: =B20*'CMV Torta de Limão'!B22
A21: Alfajor | B21: 0 | C21: =B21*135.0000/(1-PARÂMETROS!$B$6/100) | D21: =B21*('CMV Alfajor'!B22-PARÂMETROS!$D$14) | E21: =B21*'CMV Alfajor'!B22 | F21: =B21*E10 | G21: =B21*'CMV Alfajor'!B25
A22: Brigadeiro Proteico | B22: 0 | C22: =B22*140.0000/(1-PARÂMETROS!$B$6/100) | D22: =B22*('CMV Brigadeiro Proteico'!B20-PARÂMETROS!$D$14) | E22: =B22*'CMV Brigadeiro Proteico'!B20 | F22: =B22*E11 | G22: =B22*'CMV Brigadeiro Proteico'!B23
A23: TOTAL | B23: =SUM(B16:B22) | C23: =SUM(C16:C22) | D23: =SUM(D16:D22) | E23: =SUM(E16:E22) | F23: =SUM(F16:F22) | G23: =SUM(G16:G22)
A25: Preencha a coluna amarela com quantos potes de cada sabor e a planilha devolve insumo, custo total, receita e contribuição do lote.

Sheet CMV Café Proteico
A1: CMV — Café Proteico
A2: linha BOOST · 140 g de gelato por pote
A4: Ingrediente | B4: g por kg de calda | C4: g no pote | D4: R$/kg | E4: R$ no pote | F4: % do insumo
A5: LEITE ZERO LACTOSE (INTEGRAL) | B5: 655 | C5: =B5*125.5605/1000 | D5: =IFERROR(VLOOKUP(A5,PREÇOS!$A$5:$B$28,2,FALSE),0) | E5: =C5*D5/1000 | F5: =IFERROR(E5/$E$15,0)
A6: BASE MEC PROTEIN | B6: 123 | C6: =B6*125.5605/1000 | D6: =IFERROR(VLOOKUP(A6,PREÇOS!$A$5:$B$28,2,FALSE),0) | E6: =C6*D6/1000 | F6: =IFERROR(E6/$E$15,0)
A7: LEITE EM PO DESNATADO ZL (BATAVO PENSE ZERO) | B7: 113.5 | C7: =B7*125.5605/1000 | D7: =IFERROR(VLOOKUP(A7,PREÇOS!$A$5:$B$28,2,FALSE),0) | E7: =C7*D7/1000 | F7: =IFERROR(E7/$E$15,0)
A8: PASTA CAFÉ SELECTA (BALDE 2 KG) | B8: 56.8 | C8: =B8*125.5605/1000 | D8: =IFERROR(VLOOKUP(A8,PREÇOS!$A$5:$B$28,2,FALSE),0) | E8: =C8*D8/1000 | F8: =IFERROR(E8/$E$15,0)
A9: GLICEROL (GLICERINA BIDESTILADA) | B9: 28.4 | C9: =B9*125.5605/1000 | D9: =IFERROR(VLOOKUP(A9,PREÇOS!$A$5:$B$28,2,FALSE),0) | E9: =C9*D9/1000 | F9: =IFERROR(E9/$E$15,0)
A10: POLIDEXTROSE | B10: 18.9 | C10: =B10*125.5605/1000 | D10: =IFERROR(VLOOKUP(A10,PREÇOS!$A$5:$B$28,2,FALSE),0) | E10: =C10*D10/1000 | F10: =IFERROR(E10/$E$15,0)
A11: CREMOBENE PREMIUM (LIGA NEUTRA) | B11: 2.9 | C11: =B11*125.5605/1000 | D11: =IFERROR(VLOOKUP(A11,PREÇOS!$A$5:$B$28,2,FALSE),0) | E11: =C11*D11/1000 | F11: =IFERROR(E11/$E$15,0)
A12: SAL | B12: 0.9 | C12: =B12*125.5605/1000 | D12: =IFERROR(VLOOKUP(A12,PREÇOS!$A$5:$B$28,2,FALSE),0) | E12: =C12*D12/1000 | F12: =IFERROR(E12/$E$15,0)
A13: STEVIA | B13: 0.6 | C13: =B13*125.5605/1000 | D13: =IFERROR(VLOOKUP(A13,PREÇOS!$A$5:$B$28,2,FALSE),0) | E13: =C13*D13/1000 | F13: =IFERROR(E13/$E$15,0)
A14: DELÍCIA DE AMENDOIM PROTEICO | B14: 115 | C14: =B14*125.5605/1000 | D14: =IFERROR(VLOOKUP(A14,PREÇOS!$A$5:$B$28,2,FALSE),0) | E14: =C14*D14/1000 | F14: =IFERROR(E14/$E$15,0)
A15: INSUMO (sem perda) | C15: =SUM(C5:C14) | E15: =SUM(E5:E14)
A17: FECHAMENTO
A18: Linha | B18: Valor | C18: Como é calculado
A19: Insumo com perda | B19: =E15/(1-PARÂMETROS!$B$6/100) | C19: insumo ÷ (1 − perda de processo)
A20: Embalagem | B20: =PARÂMETROS!$D$14 | C20: pote + colher + lacre, da aba PARÂMETROS
A21: CMV TOTAL | B21: =B19+B20 | C21: insumo com perda + embalagem
A22: Preço de venda | B22: =VENDA!C5 | C22: da aba VENDA
A23: Imposto | B23: =B22*PARÂMETROS!$B$7/100 | C23: preço × alíquota do Simples
A24: Contribuição | B24: =B22-B21-B23 | C24: preço − CMV − imposto
A25: CMV % do preço | B25: =IFERROR(B21/B22,0) | C25: CMV ÷ preço
A26: Margem de contribuição | B26: =IFERROR(B24/B22,0) | C26: contribuição ÷ preço

Sheet CMV Pistache
A1: CMV — Pistache
A2: linha SPECIAL · 140 g de gelato por pote
A4: Ingrediente | B4: g por kg de calda | C4: g no pote | D4: R$/kg | E4: R$ no pote | F4: % do insumo
A5: LEITE ZERO LACTOSE (INTEGRAL) | B5: 654.8 | C5: =B5*140.0000/1000 | D5: =IFERROR(VLOOKUP(A5,PREÇOS!$A$5:$B$28,2,FALSE),0) | E5: =C5*D5/1000 | F5: =IFERROR(E5/$E$13,0)
A6: MIX OFICIAL | B6: 120 | C6: =B6*140.0000/1000 | D6: =IFERROR(VLOOKUP(A6,PREÇOS!$A$5:$B$28,2,FALSE),0) | E6: =C6*D6/1000 | F6: =IFERROR(E6/$E$13,0)
A7: PASTA PISTACCHIO 100% CALIFÓRNIA | B7: 90 | C7: =B7*140.0000/1000 | D7: =IFERROR(VLOOKUP(A7,PREÇOS!$A$5:$B$28,2,FALSE),0) | E7: =C7*D7/1000 | F7: =IFERROR(E7/$E$13,0)
A8: CREME DE LEITE FRESCO 35% ZL (VERDE CAMPO LACFREE) | B8: 62 | C8: =B8*140.0000/1000 | D8: =IFERROR(VLOOKUP(A8,PREÇOS!$A$5:$B$28,2,FALSE),0) | E8: =C8*D8/1000 | F8: =IFERROR(E8/$E$13,0)
A9: LEITE EM PO DESNATADO ZL (BATAVO PENSE ZERO) | B9: 33 | C9: =B9*140.0000/1000 | D9: =IFERROR(VLOOKUP(A9,PREÇOS!$A$5:$B$28,2,FALSE),0) | E9: =C9*D9/1000 | F9: =IFERROR(E9/$E$13,0)
A10: ERITRITOL | B10: 20 | C10: =B10*140.0000/1000 | D10: =IFERROR(VLOOKUP(A10,PREÇOS!$A$5:$B$28,2,FALSE),0) | E10: =C10*D10/1000 | F10: =IFERROR(E10/$E$13,0)
A11: GLICEROL (GLICERINA BIDESTILADA) | B11: 15 | C11: =B11*140.0000/1000 | D11: =IFERROR(VLOOKUP(A11,PREÇOS!$A$5:$B$28,2,FALSE),0) | E11: =C11*D11/1000 | F11: =IFERROR(E11/$E$13,0)
A12: CREMOBENE PREMIUM (LIGA NEUTRA) | B12: 5.2 | C12: =B12*140.0000/1000 | D12: =IFERROR(VLOOKUP(A12,PREÇOS!$A$5:$B$28,2,FALSE),0) | E12: =C12*D12/1000 | F12: =IFERROR(E12/$E$13,0)
A13: INSUMO (sem perda) | C13: =SUM(C5:C12) | E13: =SUM(E5:E12)
A15: FECHAMENTO
A16: Linha | B16: Valor | C16: Como é calculado
A17: Insumo com perda | B17: =E13/(1-PARÂMETROS!$B$6/100) | C17: insumo ÷ (1 − perda de processo)
A18: Embalagem | B18: =PARÂMETROS!$D$14 | C18: pote + colher + lacre, da aba PARÂMETROS
A19: CMV TOTAL | B19: =B17+B18 | C19: insumo com perda + embalagem
A20: Preço de venda | B20: =VENDA!C6 | C20: da aba VENDA
A21: Imposto | B21: =B20*PARÂMETROS!$B$7/100 | C21: preço × alíquota do Simples
A22: Contribuição | B22: =B20-B19-B21 | C22: preço − CMV − imposto
A23: CMV % do preço | B23: =IFERROR(B19/B20,0) | C23: CMV ÷ preço
A24: Margem de contribuição | B24: =IFERROR(B22/B20,0) | C24: contribuição ÷ preço

Sheet CMV Manga com Maracujá
A1: CMV — Manga com Maracujá
A2: linha FRESH · 140 g de gelato por pote
A4: Ingrediente | B4: g por kg de calda | C4: g no pote | D4: R$/kg | E4: R$ no pote | F4: % do insumo
A5: MANGA | B5: 479 | C5: =B5*140.0000/1000 | D5: =IFERROR(VLOOKUP(A5,PREÇOS!$A$5:$B$28,2,FALSE),0) | E5: =C5*D5/1000 | F5: =IFERROR(E5/$E$12,0)
A6: MARACUJA (POLPA) | B6: 235 | C6: =B6*140.0000/1000 | D6: =IFERROR(VLOOKUP(A6,PREÇOS!$A$5:$B$28,2,FALSE),0) | E6: =C6*D6/1000 | F6: =IFERROR(E6/$E$12,0)
A7: MIX OFICIAL | B7: 120 | C7: =B7*140.0000/1000 | D7: =IFERROR(VLOOKUP(A7,PREÇOS!$A$5:$B$28,2,FALSE),0) | E7: =C7*D7/1000 | F7: =IFERROR(E7/$E$12,0)
A8: AGUA | B8: 78 | C8: =B8*140.0000/1000 | D8: =IFERROR(VLOOKUP(A8,PREÇOS!$A$5:$B$28,2,FALSE),0) | E8: =C8*D8/1000 | F8: =IFERROR(E8/$E$12,0)
A9: POLIDEXTROSE | B9: 70 | C9: =B9*140.0000/1000 | D9: =IFERROR(VLOOKUP(A9,PREÇOS!$A$5:$B$28,2,FALSE),0) | E9: =C9*D9/1000 | F9: =IFERROR(E9/$E$12,0)
A10: GLICEROL (GLICERINA BIDESTILADA) | B10: 15 | C10: =B10*140.0000/1000 | D10: =IFERROR(VLOOKUP(A10,PREÇOS!$A$5:$B$28,2,FALSE),0) | E10: =C10*D10/1000 | F10: =IFERROR(E10/$E$12,0)
A11: CREMOBENE PREMIUM (LIGA NEUTRA) | B11: 3 | C11: =B11*140.0000/1000 | D11: =IFERROR(VLOOKUP(A11,PREÇOS!$A$5:$B$28,2,FALSE),0) | E11: =C11*D11/1000 | F11: =IFERROR(E11/$E$12,0)
A12: INSUMO (sem perda) | C12: =SUM(C5:C11) | E12: =SUM(E5:E11)
A14: FECHAMENTO
A15: Linha | B15: Valor | C15: Como é calculado
A16: Insumo com perda | B16: =E12/(1-PARÂMETROS!$B$6/100) | C16: insumo ÷ (1 − perda de processo)
A17: Embalagem | B17: =PARÂMETROS!$D$14 | C17: pote + colher + lacre, da aba PARÂMETROS
A18: CMV TOTAL | B18: =B16+B17 | C18: insumo com perda + embalagem
A19: Preço de venda | B19: =VENDA!C7 | C19: da aba VENDA
A20: Imposto | B20: =B19*PARÂMETROS!$B$7/100 | C20: preço × alíquota do Simples
A21: Contribuição | B21: =B19-B18-B20 | C21: preço − CMV − imposto
A22: CMV % do preço | B22: =IFERROR(B18/B19,0) | C22: CMV ÷ preço
A23: Margem de contribuição | B23: =IFERROR(B21/B19,0) | C23: contribuição ÷ preço

Sheet CMV Sorbet Morango
A1: CMV — Sorbet Morango
A2: linha FRESH · 140 g de gelato por pote
A4: Ingrediente | B4: g por kg de calda | C4: g no pote | D4: R$/kg | E4: R$ no pote | F4: % do insumo
A5: MORANGO | B5: 629 | C5: =B5*140.0000/1000 | D5: =IFERROR(VLOOKUP(A5,PREÇOS!$A$5:$B$28,2,FALSE),0) | E5: =C5*D5/1000 | F5: =IFERROR(E5/$E$12,0)
A6: MIX OFICIAL | B6: 230 | C6: =B6*140.0000/1000 | D6: =IFERROR(VLOOKUP(A6,PREÇOS!$A$5:$B$28,2,FALSE),0) | E6: =C6*D6/1000 | F6: =IFERROR(E6/$E$12,0)
A7: AGUA | B7: 98 | C7: =B7*140.0000/1000 | D7: =IFERROR(VLOOKUP(A7,PREÇOS!$A$5:$B$28,2,FALSE),0) | E7: =C7*D7/1000 | F7: =IFERROR(E7/$E$12,0)
A8: ERITRITOL | B8: 15 | C8: =B8*140.0000/1000 | D8: =IFERROR(VLOOKUP(A8,PREÇOS!$A$5:$B$28,2,FALSE),0) | E8: =C8*D8/1000 | F8: =IFERROR(E8/$E$12,0)
A9: GLICEROL (GLICERINA BIDESTILADA) | B9: 15 | C9: =B9*140.0000/1000 | D9: =IFERROR(VLOOKUP(A9,PREÇOS!$A$5:$B$28,2,FALSE),0) | E9: =C9*D9/1000 | F9: =IFERROR(E9/$E$12,0)
A10: PASTA FRAGOLA MEC3 (18047) | B10: 10 | C10: =B10*140.0000/1000 | D10: =IFERROR(VLOOKUP(A10,PREÇOS!$A$5:$B$28,2,FALSE),0) | E10: =C10*D10/1000 | F10: =IFERROR(E10/$E$12,0)
A11: CREMOBENE PREMIUM (LIGA NEUTRA) | B11: 3 | C11: =B11*140.0000/1000 | D11: =IFERROR(VLOOKUP(A11,PREÇOS!$A$5:$B$28,2,FALSE),0) | E11: =C11*D11/1000 | F11: =IFERROR(E11/$E$12,0)
A12: INSUMO (sem perda) | C12: =SUM(C5:C11) | E12: =SUM(E5:E11)
A14: FECHAMENTO
A15: Linha | B15: Valor | C15: Como é calculado
A16: Insumo com perda | B16: =E12/(1-PARÂMETROS!$B$6/100) | C16: insumo ÷ (1 − perda de processo)
A17: Embalagem | B17: =PARÂMETROS!$D$14 | C17: pote + colher + lacre, da aba PARÂMETROS
A18: CMV TOTAL | B18: =B16+B17 | C18: insumo com perda + embalagem
A19: Preço de venda | B19: =VENDA!C8 | C19: da aba VENDA
A20: Imposto | B20: =B19*PARÂMETROS!$B$7/100 | C20: preço × alíquota do Simples
A21: Contribuição | B21: =B19-B18-B20 | C21: preço − CMV − imposto
A22: CMV % do preço | B22: =IFERROR(B18/B19,0) | C22: CMV ÷ preço
A23: Margem de contribuição | B23: =IFERROR(B21/B19,0) | C23: contribuição ÷ preço

Sheet CMV Torta de Limão
A1: CMV — Torta de Limão
A2: linha SPECIAL · 140 g de gelato por pote
A4: Ingrediente | B4: g por kg de calda | C4: g no pote | D4: R$/kg | E4: R$ no pote | F4: % do insumo
A5: LEITE ZERO LACTOSE (INTEGRAL) | B5: 614 | C5: =B5*140.0000/1000 | D5: =IFERROR(VLOOKUP(A5,PREÇOS!$A$5:$B$28,2,FALSE),0) | E5: =C5*D5/1000 | F5: =IFERROR(E5/$E$13,0)
A6: MIX OFICIAL | B6: 150 | C6: =B6*140.0000/1000 | D6: =IFERROR(VLOOKUP(A6,PREÇOS!$A$5:$B$28,2,FALSE),0) | E6: =C6*D6/1000 | F6: =IFERROR(E6/$E$13,0)
A7: CREME DE LEITE FRESCO 35% ZL (VERDE CAMPO LACFREE) | B7: 102 | C7: =B7*140.0000/1000 | D7: =IFERROR(VLOOKUP(A7,PREÇOS!$A$5:$B$28,2,FALSE),0) | E7: =C7*D7/1000 | F7: =IFERROR(E7/$E$13,0)
A8: GUSTO LIMONE SICILIA (PÓ) | B8: 60 | C8: =B8*140.0000/1000 | D8: =IFERROR(VLOOKUP(A8,PREÇOS!$A$5:$B$28,2,FALSE),0) | E8: =C8*D8/1000 | F8: =IFERROR(E8/$E$13,0)
A9: LEITE EM PO DESNATADO ZL (BATAVO PENSE ZERO) | B9: 33 | C9: =B9*140.0000/1000 | D9: =IFERROR(VLOOKUP(A9,PREÇOS!$A$5:$B$28,2,FALSE),0) | E9: =C9*D9/1000 | F9: =IFERROR(E9/$E$13,0)
A10: POLIDEXTROSE | B10: 20 | C10: =B10*140.0000/1000 | D10: =IFERROR(VLOOKUP(A10,PREÇOS!$A$5:$B$28,2,FALSE),0) | E10: =C10*D10/1000 | F10: =IFERROR(E10/$E$13,0)
A11: GLICEROL (GLICERINA BIDESTILADA) | B11: 15 | C11: =B11*140.0000/1000 | D11: =IFERROR(VLOOKUP(A11,PREÇOS!$A$5:$B$28,2,FALSE),0) | E11: =C11*D11/1000 | F11: =IFERROR(E11/$E$13,0)
A12: CREMOBENE PREMIUM (LIGA NEUTRA) | B12: 6 | C12: =B12*140.0000/1000 | D12: =IFERROR(VLOOKUP(A12,PREÇOS!$A$5:$B$28,2,FALSE),0) | E12: =C12*D12/1000 | F12: =IFERROR(E12/$E$13,0)
A13: INSUMO (sem perda) | C13: =SUM(C5:C12) | E13: =SUM(E5:E12)
A15: FECHAMENTO
A16: Linha | B16: Valor | C16: Como é calculado
A17: Insumo com perda | B17: =E13/(1-PARÂMETROS!$B$6/100) | C17: insumo ÷ (1 − perda de processo)
A18: Embalagem | B18: =PARÂMETROS!$D$14 | C18: pote + colher + lacre, da aba PARÂMETROS
A19: CMV TOTAL | B19: =B17+B18 | C19: insumo com perda + embalagem
A20: Preço de venda | B20: =VENDA!C9 | C20: da aba VENDA
A21: Imposto | B21: =B20*PARÂMETROS!$B$7/100 | C21: preço × alíquota do Simples
A22: Contribuição | B22: =B20-B19-B21 | C22: preço − CMV − imposto
A23: CMV % do preço | B23: =IFERROR(B19/B20,0) | C23: CMV ÷ preço
A24: Margem de contribuição | B24: =IFERROR(B22/B20,0) | C24: contribuição ÷ preço

Sheet CMV Alfajor
A1: CMV — Alfajor
A2: linha SPECIAL · 135 g de gelato por pote + 15.0 g de cobertura
A4: Ingrediente | B4: g por kg de calda | C4: g no pote | D4: R$/kg | E4: R$ no pote | F4: % do insumo
A5: LEITE ZERO LACTOSE (INTEGRAL) | B5: 607.7 | C5: =B5*135.0000/1000 | D5: =IFERROR(VLOOKUP(A5,PREÇOS!$A$5:$B$28,2,FALSE),0) | E5: =C5*D5/1000 | F5: =IFERROR(E5/$E$16,0)
A6: DOCE DE LEITE VIÇOSA ZERO | B6: 160 | C6: =B6*135.0000/1000 | D6: =IFERROR(VLOOKUP(A6,PREÇOS!$A$5:$B$28,2,FALSE),0) | E6: =C6*D6/1000 | F6: =IFERROR(E6/$E$16,0)
A7: POLIDEXTROSE | B7: 70 | C7: =B7*135.0000/1000 | D7: =IFERROR(VLOOKUP(A7,PREÇOS!$A$5:$B$28,2,FALSE),0) | E7: =C7*D7/1000 | F7: =IFERROR(E7/$E$16,0)
A8: CREME DE LEITE FRESCO 35% ZL (VERDE CAMPO LACFREE) | B8: 60 | C8: =B8*135.0000/1000 | D8: =IFERROR(VLOOKUP(A8,PREÇOS!$A$5:$B$28,2,FALSE),0) | E8: =C8*D8/1000 | F8: =IFERROR(E8/$E$16,0)
A9: LEITE EM PO DESNATADO ZL (BATAVO PENSE ZERO) | B9: 50 | C9: =B9*135.0000/1000 | D9: =IFERROR(VLOOKUP(A9,PREÇOS!$A$5:$B$28,2,FALSE),0) | E9: =C9*D9/1000 | F9: =IFERROR(E9/$E$16,0)
A10: MALTITOL | B10: 30 | C10: =B10*135.0000/1000 | D10: =IFERROR(VLOOKUP(A10,PREÇOS!$A$5:$B$28,2,FALSE),0) | E10: =C10*D10/1000 | F10: =IFERROR(E10/$E$16,0)
A11: GLICEROL (GLICERINA BIDESTILADA) | B11: 15 | C11: =B11*135.0000/1000 | D11: =IFERROR(VLOOKUP(A11,PREÇOS!$A$5:$B$28,2,FALSE),0) | E11: =C11*D11/1000 | F11: =IFERROR(E11/$E$16,0)
A12: CREMOBENE PREMIUM (LIGA NEUTRA) | B12: 6 | C12: =B12*135.0000/1000 | D12: =IFERROR(VLOOKUP(A12,PREÇOS!$A$5:$B$28,2,FALSE),0) | E12: =C12*D12/1000 | F12: =IFERROR(E12/$E$16,0)
A13: SAL | B13: 1 | C13: =B13*135.0000/1000 | D13: =IFERROR(VLOOKUP(A13,PREÇOS!$A$5:$B$28,2,FALSE),0) | E13: =C13*D13/1000 | F13: =IFERROR(E13/$E$16,0)
A14: STEVIA | B14: 0.3 | C14: =B14*135.0000/1000 | D14: =IFERROR(VLOOKUP(A14,PREÇOS!$A$5:$B$28,2,FALSE),0) | E14: =C14*D14/1000 | F14: =IFERROR(E14/$E$16,0)
A15: BISCOITO ALFAJOR DE CHOCOLATE (ZERO LACTOSE) | B15: 111 | C15: =B15*135.0000/1000 | D15: =IFERROR(VLOOKUP(A15,PREÇOS!$A$5:$B$28,2,FALSE),0) | E15: =C15*D15/1000 | F15: =IFERROR(E15/$E$16,0)
A16: INSUMO (sem perda) | C16: =SUM(C5:C15) | E16: =SUM(E5:E15)
A18: FECHAMENTO
A19: Linha | B19: Valor | C19: Como é calculado
A20: Insumo com perda | B20: =E16/(1-PARÂMETROS!$B$6/100) | C20: insumo ÷ (1 − perda de processo)
A21: Embalagem | B21: =PARÂMETROS!$D$14 | C21: pote + colher + lacre, da aba PARÂMETROS
A22: CMV TOTAL | B22: =B20+B21 | C22: insumo com perda + embalagem
A23: Preço de venda | B23: =VENDA!C10 | C23: da aba VENDA
A24: Imposto | B24: =B23*PARÂMETROS!$B$7/100 | C24: preço × alíquota do Simples
A25: Contribuição | B25: =B23-B22-B24 | C25: preço − CMV − imposto
A26: CMV % do preço | B26: =IFERROR(B22/B23,0) | C26: CMV ÷ preço
A27: Margem de contribuição | B27: =IFERROR(B25/B23,0) | C27: contribuição ÷ preço

Sheet CMV Brigadeiro Proteico
A1: CMV — Brigadeiro Proteico
A2: linha BOOST · 140 g de gelato por pote
A4: Ingrediente | B4: g por kg de calda | C4: g no pote | D4: R$/kg | E4: R$ no pote | F4: % do insumo
A5: LEITE ZERO LACTOSE (INTEGRAL) | B5: 668.5 | C5: =B5*140.0000/1000 | D5: =IFERROR(VLOOKUP(A5,PREÇOS!$A$5:$B$28,2,FALSE),0) | E5: =C5*D5/1000 | F5: =IFERROR(E5/$E$14,0)
A6: BASE MEC PROTEIN | B6: 125 | C6: =B6*140.0000/1000 | D6: =IFERROR(VLOOKUP(A6,PREÇOS!$A$5:$B$28,2,FALSE),0) | E6: =C6*D6/1000 | F6: =IFERROR(E6/$E$14,0)
A7: LEITE EM PO DESNATADO ZL (BATAVO PENSE ZERO) | B7: 115.4 | C7: =B7*140.0000/1000 | D7: =IFERROR(VLOOKUP(A7,PREÇOS!$A$5:$B$28,2,FALSE),0) | E7: =C7*D7/1000 | F7: =IFERROR(E7/$E$14,0)
A8: CACAU 22/24 | B8: 38.5 | C8: =B8*140.0000/1000 | D8: =IFERROR(VLOOKUP(A8,PREÇOS!$A$5:$B$28,2,FALSE),0) | E8: =C8*D8/1000 | F8: =IFERROR(E8/$E$14,0)
A9: GLICEROL (GLICERINA BIDESTILADA) | B9: 28.9 | C9: =B9*140.0000/1000 | D9: =IFERROR(VLOOKUP(A9,PREÇOS!$A$5:$B$28,2,FALSE),0) | E9: =C9*D9/1000 | F9: =IFERROR(E9/$E$14,0)
A10: POLIDEXTROSE | B10: 19.2 | C10: =B10*140.0000/1000 | D10: =IFERROR(VLOOKUP(A10,PREÇOS!$A$5:$B$28,2,FALSE),0) | E10: =C10*D10/1000 | F10: =IFERROR(E10/$E$14,0)
A11: CREMOBENE PREMIUM (LIGA NEUTRA) | B11: 3 | C11: =B11*140.0000/1000 | D11: =IFERROR(VLOOKUP(A11,PREÇOS!$A$5:$B$28,2,FALSE),0) | E11: =C11*D11/1000 | F11: =IFERROR(E11/$E$14,0)
A12: SAL | B12: 1 | C12: =B12*140.0000/1000 | D12: =IFERROR(VLOOKUP(A12,PREÇOS!$A$5:$B$28,2,FALSE),0) | E12: =C12*D12/1000 | F12: =IFERROR(E12/$E$14,0)
A13: STEVIA | B13: 0.6 | C13: =B13*140.0000/1000 | D13: =IFERROR(VLOOKUP(A13,PREÇOS!$A$5:$B$28,2,FALSE),0) | E13: =C13*D13/1000 | F13: =IFERROR(E13/$E$14,0)
A14: INSUMO (sem perda) | C14: =SUM(C5:C13) | E14: =SUM(E5:E13)
A16: FECHAMENTO
A17: Linha | B17: Valor | C17: Como é calculado
A18: Insumo com perda | B18: =E14/(1-PARÂMETROS!$B$6/100) | C18: insumo ÷ (1 − perda de processo)
A19: Embalagem | B19: =PARÂMETROS!$D$14 | C19: pote + colher + lacre, da aba PARÂMETROS
A20: CMV TOTAL | B20: =B18+B19 | C20: insumo com perda + embalagem
A21: Preço de venda | B21: =VENDA!C11 | C21: da aba VENDA
A22: Imposto | B22: =B21*PARÂMETROS!$B$7/100 | C22: preço × alíquota do Simples
A23: Contribuição | B23: =B21-B20-B22 | C23: preço − CMV − imposto
A24: CMV % do preço | B24: =IFERROR(B20/B21,0) | C24: CMV ÷ preço
A25: Margem de contribuição | B25: =IFERROR(B23/B21,0) | C25: contribuição ÷ preço
